<ZT2Strings>
      <LOC_STRING _locID="zoonames:wetlandconsv"  >Wetland Conservation</LOC_STRING>
      <LOC_STRING _locID="zoonames:tundraice"  >Tundra Ice Chasm</LOC_STRING>
      <LOC_STRING _locID="zoonames:temperategum"  >Gum Tree Grove</LOC_STRING>
      <LOC_STRING _locID="zoonames:scrubmesa"  >Scrub Central Mesa</LOC_STRING>
      <LOC_STRING _locID="zoonames:desertoasis"  >Desert Oasis</LOC_STRING>
      <LOC_STRING _locID="zoonames:borealsequoia"  >Sequoia Grove</LOC_STRING>
      <LOC_STRING _locID="zoonames:alpinemount"  >Alpine Mountain</LOC_STRING>
      <LOC_STRING _locID="zoonames:savannahsanct"  >Savannah Sanctuary</LOC_STRING>
      <LOC_STRING _locID="zoonames:grasslandcrat"  >Grassland Crater</LOC_STRING>
      <LOC_STRING _locID="zoonames:grasslandjr"  >City Zoo Junior</LOC_STRING>
      <LOC_STRING _locID="zoonames:tropicalruin"  >Tropical Ruins</LOC_STRING>
      <LOC_STRING _locID="zoonames:xp1endangered1"  >Baird's Tapir Zoo</LOC_STRING>
      <LOC_STRING _locID="zoonames:xp1endangered2"  >Breeding Program Zoo</LOC_STRING>
      <LOC_STRING _locID="zoonames:xp1endangered3"  >Endangered Animals Zoo</LOC_STRING>
      <LOC_STRING _locID="zoonames:xp1transportation1"  >Great Savannah Zoo</LOC_STRING>
      <LOC_STRING _locID="zoonames:xp1transportation2"  >Bridging the Gap Zoo</LOC_STRING>
      <LOC_STRING _locID="zoonames:xp1transportation3"  >Reach for the Stars Zoo</LOC_STRING>
      <LOC_STRING _locID="zoonames:xp1photosafari1"  >VIPs Zoo</LOC_STRING>
      <LOC_STRING _locID="zoonames:xp1photosafari2"  >Javan Rhino Zoo</LOC_STRING>
      <LOC_STRING _locID="zoonames:xp1photosafari3"  >Cat Sanctuary Zoo</LOC_STRING>
      <LOC_STRING _locID="zoonames:xp1tutorialone"  >Tutorial Zoo</LOC_STRING>
      <LOC_STRING _locID="zoonames:xp1tutorialtwo"  >Tutorial Zoo</LOC_STRING>
      <LOC_STRING _locID="zoonames:xp1tutorialthree"  >Tutorial Zoo</LOC_STRING>
</ZT2Strings>
