<soundtags>
   <BFSoundtag>
      <BF3DSndFactory name="GorillaMountain_Adult_Eat">
         <snd name="entities/units/animals/GorillaMountain/sound/GorillaMountain_Adult_EatA.wav" volume="1" mindist="8" maxdist="25"/>
      </BF3DSndFactory>
   </BFSoundtag>
   <BFSoundtag>
      <BF3DSndFactory name="GorillaMountain_Adult_QuestionBark">
         <snd name="entities/units/animals/GorillaMountain/sound/GorillaMountain_Adult_QuestionBark.wav" volume="1.2" mindist="10" maxdist="50"/>
      </BF3DSndFactory>
   </BFSoundtag>
   <BFSoundtag>
      <BF3DSndFactory name="GorillaMountain_Adult_HootBark">
         <snd name="entities/units/animals/GorillaMountain/sound/GorillaMountain_Adult_QuestionBark.wav" volume="1.2" mindist="8" maxdist="50"/>
      </BF3DSndFactory>
   </BFSoundtag>
   <BFSoundtag>
      <BF3DSndFactory name="GorillaMountain_Adult_Drum">
         <snd name="entities/units/animals/GorillaMountain/sound/GorillaMountain_Adult_Drum.wav" volume="1" mindist="6" maxdist="50"/>
      </BF3DSndFactory>
   </BFSoundtag>
   <BFSoundtag>
      <BF3DSndFactory name="GorillaMountain_Adult_Chuckle">
         <snd name="entities/units/animals/GorillaMountain/sound/GorillaMountain_Adult_Chuckle.wav" volume="1" mindist="6" maxdist="50"/>
      </BF3DSndFactory>
   </BFSoundtag>
   <BFSoundtag>
      <BF3DSndFactory name="GorillaMountain_Adult_Sleep">
         <snd name="entities/units/animals/GorillaMountain/sound/GorillaMountain_Adult_Sleep.wav" volume="1" mindist="6" maxdist="25"/>
      </BF3DSndFactory>
   </BFSoundtag>
   <BFSoundtag>
      <BF3DSndFactory name="GorillaMountain_Adult_Growl">
         <snd name="entities/units/animals/GorillaMountain/sound/GorillaMountain_Adult_GrowlA.wav" volume="1.2" mindist="10" maxdist="50"/>
      </BF3DSndFactory>
   </BFSoundtag>
   <BFSoundtag>
      <BF3DSndFactory name="GorillaMountain_Adult_Kiss">
         <snd name="entities/units/animals/GorillaMountain/sound/GorillaMountain_Young_Kiss.wav" volume="1" mindist="8" maxdist="25"/>
      </BF3DSndFactory>
   </BFSoundtag>
   <BFSoundtag>
      <BF3DSndFactory name="GorillaMountain_Adult_Scream">
         <snd name="entities/units/animals/GorillaMountain/sound/GorillaMountain_Adult_ScreamA.wav" volume="1.2" mindist="10" maxdist="50"/>
      </BF3DSndFactory>
   </BFSoundtag>
   <BFSoundtag>
      <BF3DSndFactory name="GorillaMountain_Adult_Sneeze">
         <snd name="entities/units/animals/GorillaMountain/sound/GorillaMountain_Adult_Sneeze.wav" volume="1" mindist="10" maxdist="25"/>
      </BF3DSndFactory>
   </BFSoundtag>
   <BFSoundtag>
      <BF3DSndFactory name="GorillaMountain_Adult_Grunt">
         <snd name="entities/units/animals/GorillaMountain/sound/GorillaMountain_Adult_GruntA.wav" volume="1" mindist="10" maxdist="25"/>
      </BF3DSndFactory>
   </BFSoundtag>
   <BFSoundtag>
      <BF3DSndFactory name="GorillaMountain_Adult_Belch">
         <snd name="entities/units/animals/GorillaMountain/sound/GorillaMountain_Adult_Belch.wav" volume="1" mindist="10" maxdist="25"/>
      </BF3DSndFactory>
   </BFSoundtag>
   <BFSoundtag>
      <BF3DSndFactory name="GorillaMountain_Adult_Yawn">
         <snd name="entities/units/animals/GorillaMountain/sound/GorillaMountain_Adult_Yawn.wav" volume="1" mindist="8" maxdist="25"/>
      </BF3DSndFactory>
   </BFSoundtag>
   <BFSoundtag>
      <BF3DSndFactory name="GorillaMountain_Adult_Spit">
         <snd name="entities/units/animals/shared/sound/CamelDromedary_Young_SpitA.wav" volume="1" mindist="6" maxdist="25"/>
      </BF3DSndFactory>
   </BFSoundtag>
   <!--Young-->
   <BFSoundtag>
      <BF3DSndFactory name="GorillaMountain_Young_Eat">
         <snd name="entities/units/animals/GorillaMountain/sound/GorillaMountain_Young_EatA.wav" volume="1" mindist="8" maxdist="25"/>
      </BF3DSndFactory>
   </BFSoundtag>
   <BFSoundtag>
      <BF3DSndFactory name="GorillaMountain_Young_QuestionBark">
         <snd name="entities/units/animals/GorillaMountain/sound/GorillaMountain_Young_QuestionBark.wav" volume="1" mindist="10" maxdist="50"/>
      </BF3DSndFactory>
   </BFSoundtag>
   <BFSoundtag>
      <BF3DSndFactory name="GorillaMountain_Young_Drum">
         <snd name="entities/units/animals/GorillaMountain/sound/GorillaMountain_Young_Drum.wav" volume="1" mindist="4" maxdist="50"/>
      </BF3DSndFactory>
   </BFSoundtag>
   <BFSoundtag>
      <BF3DSndFactory name="GorillaMountain_Young_Chuckle">
         <snd name="entities/units/animals/GorillaMountain/sound/GorillaMountain_Young_Chuckle.wav" volume="1" mindist="4" maxdist="50"/>
      </BF3DSndFactory>
   </BFSoundtag>
   <BFSoundtag>
      <BF3DSndFactory name="GorillaMountain_Young_Sleep">
         <snd name="entities/units/animals/GorillaMountain/sound/GorillaMountain_Young_Sleep.wav" volume="1" mindist="6" maxdist="25"/>
      </BF3DSndFactory>
   </BFSoundtag>
   <BFSoundtag>
      <BF3DSndFactory name="GorillaMountain_Young_Growl">
         <snd name="entities/units/animals/GorillaMountain/sound/GorillaMountain_Young_GrowlA.wav" volume="1" mindist="10" maxdist="50"/>
      </BF3DSndFactory>
   </BFSoundtag>
   <BFSoundtag>
      <BF3DSndFactory name="GorillaMountain_Young_Kiss">
         <snd name="entities/units/animals/GorillaMountain/sound/GorillaMountain_Young_Kiss.wav" volume="1" mindist="8" maxdist="25"/>
      </BF3DSndFactory>
   </BFSoundtag>
   <BFSoundtag>
      <BF3DSndFactory name="GorillaMountain_Young_Scream">
         <snd name="entities/units/animals/GorillaMountain/sound/GorillaMountain_Young_ScreamA.wav" volume="1" mindist="10" maxdist="50"/>
      </BF3DSndFactory>
   </BFSoundtag>
   <BFSoundtag>
      <BF3DSndFactory name="GorillaMountain_Young_Sneeze">
         <snd name="entities/units/animals/GorillaMountain/sound/GorillaMountain_Young_Sneeze.wav" volume="1" mindist="4" maxdist="25"/>
      </BF3DSndFactory>
   </BFSoundtag>
   <BFSoundtag>
      <BF3DSndFactory name="GorillaMountain_Young_Belch">
         <snd name="entities/units/animals/GorillaMountain/sound/GorillaMountain_Young_Belch.wav" volume="1" mindist="6" maxdist="25"/>
      </BF3DSndFactory>
   </BFSoundtag>
   <BFSoundtag>
      <BF3DSndFactory name="GorillaMountain_Young_Yawn">
         <snd name="entities/units/animals/GorillaMountain/sound/GorillaMountain_Young_Yawn.wav" volume="1" mindist="4" maxdist="25"/>
      </BF3DSndFactory>
   </BFSoundtag>
   <BFSoundtag>
      <BF3DSndFactory name="GorillaMountain_Young_Grunt">
         <snd name="entities/units/animals/GorillaMountain/sound/GorillaMountain_Young_GruntA.wav" volume="1.2" mindist="6" maxdist="50"/>
      </BF3DSndFactory>
   </BFSoundtag>
   <!--Shared Sounds-->
   <BFSoundtag>
      <BF3DSndFactory name="GorillaMountain_pawground_dirt">
         <snd name="entities/units/animals/shared/sound/Animal_PawDirt_SoftA.wav" volume="1" mindist="2" maxdist="50"/>
      </BF3DSndFactory>
   </BFSoundtag>
   <BFSoundtag>
      <BF3DSndFactory name="GorillaMountain_pawground_grassland">
         <snd name="entities/units/animals/shared/sound/Animal_PawGrass_SoftA.wav" volume="1" mindist="2" maxdist="50"/>
      </BF3DSndFactory>
   </BFSoundtag>
   <BFSoundtag>
      <BF3DSndFactory name="GorillaMountain_pawground_tundra">
         <snd name="entities/units/animals/shared/sound/Animal_PawSnow_SoftA.wav" volume="1" mindist="2" maxdist="50"/>
      </BF3DSndFactory>
   </BFSoundtag>
</soundtags>
